{
  "dataList": [
    {
      "id": 0,
      "place": "A bordo de Mefistófeles",
      "content": "Una Charon con mala cara y la fría mirada de Vergilius nos esperaban en el bus..."
    },
    {
      "id": 1,
      "content": "El aire pesaba con una sensación de opresión, dejando pequeño espacio para bromas alegres."
    },
    {
      "id": 2,
      "model": "카론",
      "content": "Llegan tarde. Charon contó hasta cien y aun así no vinieron."
    },
    {
      "id": 3,
      "model": "베르길리우스2",
      "teller": "Vergilius",
      "title": "Guía",
      "content": "Charon."
    },
    {
      "id": 4,
      "content": "Parecía que tenía pocas palabras extra listas para ser lanzadas en ese frío tono, pero Vergilius puso una mano en su hombro y le dio una mirada."
    },
    {
      "id": 5,
      "model": "카론",
      "content": "Verg, Charon recordará esto."
    },
    {
      "id": 6,
      "model": "베르길리우스2",
      "teller": "Vergilius",
      "title": "Guía",
      "content": "Discúlpame. Te compraré algo dulce luego."
    },
    {
      "id": 7,
      "content": "Charon se sentó en el asiento del conductor sin más quejas, y Vergilius se tornó a nosotros lentamente."
    },
    {
      "id": 8,
      "content": "Si hubiese una cosa en la que los Pecadores y yo éramos buenos, sería en sentir peligro inminente y hacernos camino."
    },
    {
      "id": 9,
      "content": "Dispersándonos, nos hundimos en nuestros asientos..."
    },
    {
      "id": 10,
      "content": "Dejando sólo a Don Quixote parada ansiosamente en el pasillo del bus."
    },
    {
      "id": 11,
      "model": "베르길리우스2",
      "teller": "Vergilius",
      "title": "Guía",
      "content": "Escuchemos tu excusa, Don Quixote."
    },
    {
      "id": 12,
      "model": "돈키호테",
      "content": "No podía... hacer la vista gorda a los débiles siendo perseguidos—"
    },
    {
      "id": 13,
      "model": "베르길리우스2",
      "teller": "Vergilius",
      "title": "Guía",
      "content": "No, mal."
    },
    {
      "id": 14,
      "content": "Mi vista no pudo seguir lo que pasó en ese instante."
    },
    {
      "id": 15,
      "content": "No tengo nada con lo que parpadear, así que no debía haber sido posible que me pierda un solo momento, y aun así..."
    },
    {
      "id": 16,
      "model": "돈키호테",
      "content": "¡Gahgk…! Ghk…"
    },
    {
      "id": 17,
      "content": "Cuando me di cuenta de la situación..."
    },
    {
      "id": 18,
      "content": "La primera cosa que pude notar era Don Quixote en el suelo, con su hombro pisoteado bajo el zapato de Vergilius."
    },
    {
      "id": 19,
      "model": "베르길리우스2",
      "teller": "Vergilius",
      "title": "Guía",
      "content": "Pedí una excusa. No una justificación de tus ideales."
    },
    {
      "id": 20,
      "model": "돈키호테",
      "content": "¡Gnnngh…!"
    },
    {
      "id": 21,
      "model": "베르길리우스2",
      "teller": "Vergilius",
      "title": "Guía",
      "content": "Esta tampoco es la primera vez, Don Quixote. Ya eres responsable de tres incidentes distintos."
    },
    {
      "id": 22,
      "model": "베르길리우스2",
      "teller": "Vergilius",
      "title": "Guía",
      "content": "Son tres veces diferentes que has comprometido nuestro trabajo con tu comportamiento trastornado."
    },
    {
      "id": 23,
      "model": "베르길리우스2",
      "teller": "Vergilius",
      "title": "Guía",
      "content": "¿Qué es lo que piensas? Habla."
    },
    {
      "id": 24,
      "model": "돈키호테",
      "content": "Si... Si bien mis propias acciones causaron adversidades para mis colegas..."
    },
    {
      "id": 25,
      "model": "돈키호테",
      "content": "Hngk… ¡¡¡GUAAAH!!!"
    },
    {
      "id": 26,
      "content": "Las quejas dolidas de Don Quixote se hacían más fuertes, pero nadie intervino."
    },
    {
      "id": 27,
      "content": "Por supuesto, estaba siendo castigada por sus propias acciones..."
    },
    {
      "id": 28,
      "content": "Pero más que nada, era evidente de perturbar esto no iba a mejorar la situación."
    },
    {
      "id": 29,
      "model": "베르길리우스2",
      "teller": "Vergilius",
      "title": "Guía",
      "content": "Estaba preguntando por lo que piensas. ¿Por qué no lo entiendes?"
    },
    {
      "id": 30,
      "model": "돈키호테",
      "content": "¡E-Estaba hablando sólo para ser interrumpida!"
    },
    {
      "id": 31,
      "model": "베르길리우스2",
      "teller": "Vergilius",
      "title": "Guía",
      "content": "Lo que debiste decirme desde el principio era una disculpa, Don Quixote."
    },
    {
      "id": 32,
      "model": "베르길리우스2",
      "teller": "Vergilius",
      "title": "Guía",
      "content": "Cualquier otra cosa que añadir debería ser una explicación de como planeas mejorar tu conducta."
    },
    {
      "id": 33,
      "model": "돈키호테",
      "content": "Que injusti... ¡Agh! ¡Vos estáis demandando una respuesta específica de mi persona...!"
    },
    {
      "id": 34,
      "model": "베르길리우스2",
      "teller": "Vergilius",
      "title": "Guía",
      "content": "¿No lo sabes? Una compañía ya tiene las respuestas \"correctas\" para sus empleados. Las preguntas sólo se hacen para ver si es que puedes hacerlo bien."
    },
    {
      "id": 35,
      "model": "베르길리우스2",
      "teller": "Vergilius",
      "title": "Guía",
      "content": "Estás seriamente equivocada si es que crees que la compañía está sinceramente curiosa por tu aporte."
    },
    {
      "id": 36,
      "model": "돈키호테",
      "content": "Kagh… ¡Si-si la compañía lo insiste, entonces yo he—!"
    },
    {
      "id": 37,
      "model": "베르길리우스2",
      "teller": "Vergilius",
      "title": "Guía",
      "content": "... Estoy harto de esto."
    },
    {
      "id": 38,
      "content": "Vergilius pateó a Don Quixote, lanzándola al piso."
    },
    {
      "id": 39,
      "content": "Luego, agarrándola del cuello..."
    },
    {
      "id": 40,
      "model": "베르길리우스2",
      "teller": "Vergilius",
      "title": "Guía",
      "content": "Estoy seguro que recuerdas lo que pasó cuando te uniste."
    },
    {
      "id": 41,
      "model": "돈키호테",
      "content": "¡…!"
    },
    {
      "id": 42,
      "model": "베르길리우스",
      "content": "Espero que no hayas olvidado el trato que cerramos ese día... Señorita. Don. Quixote."
    },
    {
      "id": 43,
      "content": "Los ojos de Vergilius brillaron con un tono de rojo mucho más reluciente de lo normal.."
    },
    {
      "id": 44,
      "content": "Mirándolos directamente, Don Quixote pronto asintió sin decir otra palabra."
    },
    {
      "id": 45,
      "model": "베르길리우스2",
      "teller": "Vergilius",
      "title": "Guía",
      "content": "... Eso es todo. De vuelta a tu sitio."
    },
    {
      "id": 46,
      "content": "Ver a alguien que usualmente exudaba orgullo y seguridad rápidamente cambiar a un estado tan desanimado y cabizbajo no era exactamente muy agradable de ver."
    },
    {
      "id": 47,
      "content": "Aunque, un trato que hizo a Don Quixote silenciarse simplemente mencionándolo..."
    },
    {
      "id": 48,
      "content": "Me hace preguntar sobre qué era."
    },
    {
      "id": 49,
      "model": "베르길리우스2",
      "teller": "Vergilius",
      "title": "Guía",
      "content": "Lo mismo va para el resto de ustedes."
    },
    {
      "id": 50,
      "model": "베르길리우스2",
      "teller": "Vergilius",
      "title": "Guía",
      "content": "Una compañía no es un medio para cumplir sueños egocéntricos o predicar ideas grandes."
    },
    {
      "id": 51,
      "model": "베르길리우스2",
      "teller": "Vergilius",
      "title": "Guía",
      "content": "Si aun así decidiesen ir contra los términos de su contrato de empleabilidad para salirse de la línea, consideren las consecuencias antes de hacerlo."
    },
    {
      "id": 52,
      "model": "베르길리우스2",
      "teller": "Vergilius",
      "title": "Guía",
      "content": "Pasarán un agotador periodo de ser incapaces de escapar. No podrán morir, y por más que lo quisieran, tampoco renunciar."
    },
    {
      "id": 53,
      "model": "그레고르",
      "content": "Supongo que conseguir ayuda de ese tipo... quién era... el señor... Zack Frito, o lo que sea... debe haberlo irritado incluso más.."
    },
    {
      "id": 54,
      "model": "돈키호테",
      "content": "Es... Señor Siegfried..."
    },
    {
      "id": 55,
      "model": "로쟈",
      "content": "Caramba, la misión ni siquiera ha empezado y ya nos conseguimos un regaño~ ¿Ten un poquito más tacto antes de actuar, sí?"
    },
    {
      "id": 56,
      "model": "이스마엘",
      "content": "Uff... Sabía que este día vendría tarde o temprano. Deberíamos ser más cuidados desde ahora."
    },
    {
      "id": 57,
      "model": "히스클리프",
      "content": "¿Qué me miran ustedes dos? ¿Quieren que los mate?"
    },
    {
      "id": 58,
      "model": "베르길리우스2",
      "teller": "Vergilius",
      "title": "Guía",
      "content": "……"
    },
    {
      "id": 59,
      "model": "히스클리프",
      "content": "... ¡Bueno! ¡Ya entendí, ya entendí! Tsk."
    }
  ]
}