{
  "dataList": [
    {
      "id": 2110511,
      "levelList": [
        {
          "level": 1,
          "name": "Felices Fiestas",
          "abName": "Sandolfo",
          "desc": "",
          "coinlist": [
            {
              "coindescs": [
                {
                  "desc": "[OnSucceedAttack] Provoca [VibrationExplosion]"
                },
                {
                  "desc": "[EndSkill] Aplica 1 'Daño Aumentado' para la Afinidad con la mayor cuenta de Resonancia a 2 aliados con los menores PC"
                },
                {
                  "desc": "[EndSkill] Cura 20 PC para 2 aliados con los menores PC"
                }
              ]
            }
          ]
        },
        {
          "level": 3,
          "name": "Felices Fiestas",
          "abName": "Sandolfo",
          "desc": "",
          "coinlist": [
            {
              "coindescs": [
                {
                  "desc": "[OnSucceedAttack] Provoca [VibrationExplosion]"
                },
                {
                  "desc": "[EndSkill] Aplica 1 'Daño Aumentado' para la Afinidad con la mayor cuenta de Resonancia a 3 aliados con los menores PC"
                },
                {
                  "desc": "[EndSkill] Cura 20 PC para 3 aliados con los menores PC"
                }
              ]
            }
          ]
        },
        {
          "level": 4,
          "name": "Felices Fiestas",
          "abName": "Sandolfo",
          "desc": "",
          "coinlist": [
            {
              "coindescs": [
                {
                  "desc": "[OnSucceedAttack] Provoca [VibrationExplosion]"
                },
                {
                  "desc": "[EndSkill] Aplica 1 'Daño Aumentado' para la Afinidad con la mayor cuenta de Resonancia a 4 aliados con los menores PC"
                },
                {
                  "desc": "[EndSkill] Cura 20 PC para 4 aliados con los menores PC"
                }
              ]
            }
          ]
        }
      ]
    },
    {
      "id": 2110521,
      "levelList": [
        {
          "level": 1,
          "name": "Felices Fiestas",
          "abName": "Sandolfo",
          "desc": "[CantIdentify]\nObjetivo seleccionado aleatoriamente\n[BeforeAttack] Esta unidad pierde 10% de HP",
          "coinlist": [
            {
              "coindescs": [
                {
                  "desc": "[OnSucceedAttack] Objetivo pierde 10 PC"
                },
                {
                  "desc": "[OnSucceedAttack] Provoca [VibrationExplosion]"
                },
                {
                  "desc": "[OnSucceedAttackTail] Inflige 1 Fragilidad para la Afinidad con la mayor cuenta de Resonancia"
                }
              ]
            }
          ]
        },
        {
          "level": 3,
          "name": "Felices Fiestas",
          "abName": "Sandolfo",
          "desc": "[CantIdentify]\nObjetivo seleccionado aleatoriamente\n[BeforeAttack] Esta unidad pierde 10% de HP",
          "coinlist": [
            {
              "coindescs": [
                {
                  "desc": "[OnSucceedAttack] Objetivo pierde 10 PC"
                },
                {
                  "desc": "[OnSucceedAttack] Provoca [VibrationExplosion]"
                },
                {
                  "desc": "[OnSucceedAttackTail] Inflige 2 Fragilidad para la Afinidad con la mayor cuenta de Resonancia"
                },
                {
                  "desc": "[EndSkillTail] Gana 1 'Daño Aumentado' para la Afinidad con la mayor cuenta de Resonancia"
                }
              ]
            }
          ]
        },
        {
          "level": 4,
          "name": "Felices Fiestas",
          "abName": "Sandolfo",
          "desc": "[CantIdentify]\nObjetivo seleccionado aleatoriamente\n[BeforeAttack] Esta unidad pierde 10% de HP",
          "coinlist": [
            {
              "coindescs": [
                {
                  "desc": "[OnSucceedAttack] Objetivo pierde 10 PC"
                },
                {
                  "desc": "[OnSucceedAttack] Provoca [VibrationExplosion]"
                },
                {
                  "desc": "[OnSucceedAttack] Inflige 2 Fragilidad para la Afinidad con la mayor cuenta de Resonancia"
                },
                {
                  "desc": "[EndSkillTail] Gana 1 'Daño Aumentado' para la Afinidad con la mayor cuenta de Resonancia"
                }
              ]
            }
          ]
        }
      ]
    },
    {
      "id": 2110611,
      "levelList": [
        {
          "level": 1,
          "name": "Ataduras",
          "abName": "El Rey en Ataduras",
          "desc": "[BeforeAttack] Gana (Reson. más alta de Orgullo o Pereza - 2) Alcance de Atq (máx 2)\n[EndSkill] Por 3 turnos, pierde 10 PC al Final del Turno",
          "coinlist": [
            {
              "coindescs": [
                {
                  "desc": "[OnSucceedAttack] Inflige 4 de [Vibration]"
                },
                {
                  "desc": "[OnSucceedAttack] Provoca [Switch_Vibration] en [VibrationCrack]"
                },
                {
                  "desc": "[OnSucceedAttack] Provoca [VibrationExplosion]"
                }
              ]
            }
          ]
        },
        {
          "level": 3,
          "name": "Ataduras",
          "abName": "El Rey en Ataduras",
          "desc": "[BeforeAttack] Gana (Reson. más alta de Orgullo o Pereza - 2) Alcance de Atq (máx 2)\nUmbral de Aturdimiento incrementado por [VibrationExplosion] aumenta en un 50%\n[EndSkill] Por 3 turnos, pierde 9 PC al Final del Turno",
          "coinlist": [
            {
              "coindescs": [
                {
                  "desc": "[OnSucceedAttack] Inflige 5 de [Vibration]"
                },
                {
                  "desc": "[OnSucceedAttack] Provoca [Switch_Vibration] en [VibrationCrack]"
                },
                {
                  "desc": "[OnSucceedAttack] Provoca [VibrationExplosion]"
                }
              ]
            }
          ]
        },
        {
          "level": 4,
          "name": "Ataduras",
          "abName": "El Rey en Ataduras",
          "desc": "[BeforeAttack] Gana (Reson. más alta de Orgullo o Pereza - 2) Alcance de Atq (máx 2)\nUmbral de Aturdimiento incrementado por [VibrationExplosion] aumenta en un 100%\n[EndSkill] Por 3 turnos, pierde 8 PC al Final del Turno",
          "coinlist": [
            {
              "coindescs": [
                {
                  "desc": "[OnSucceedAttack] Inflige 6 de [Vibration]"
                },
                {
                  "desc": "[OnSucceedAttack] Provoca [Switch_Vibration] en [VibrationCrack]"
                },
                {
                  "desc": "[OnSucceedAttack] Provoca [VibrationExplosion]"
                }
              ]
            }
          ]
        }
      ]
    },
    {
      "id": 2110621,
      "levelList": [
        {
          "level": 1,
          "name": "Ataduras",
          "abName": "El Rey en Ataduras",
          "desc": "[CantIdentify]\nObjetivo seleccionado aleatoriamente\n[BeforeAttack] Gana (Reson. más alta de Orgullo o Pereza - 2) Alcance de Atq (máx 2)",
          "coinlist": [
            {
              "coindescs": [
                {
                  "desc": "[OnSucceedAttack] Inflige 4 de [Vibration]"
                },
                {
                  "desc": "[OnSucceedAttack] Inflige +2 Contador de [Vibration]"
                },
                {
                  "desc": "[OnSucceedAttack] Provoca [Switch_Vibration] en [VibrationCrack]"
                },
                {
                  "desc": "[OnSucceedAttack] Provoca [VibrationExplosion]"
                }
              ]
            }
          ]
        },
        {
          "level": 3,
          "name": "Ataduras",
          "abName": "El Rey en Ataduras",
          "desc": "[CantIdentify]\nObjetivo seleccionado aleatoriamente\n[BeforeAttack] Gana (Reson. más alta de Orgullo o Pereza - 2) Alcance de Atq (máx 2)\nUmbral de Aturdimiento incrementado por [VibrationExplosion] aumenta en un 50%",
          "coinlist": [
            {
              "coindescs": [
                {
                  "desc": "[OnSucceedAttack] Inflige 5 de [Vibration]"
                },
                {
                  "desc": "[OnSucceedAttack] Inflige +2 Contador de [Vibration]"
                },
                {
                  "desc": "[OnSucceedAttack] Provoca [Switch_Vibration] en [VibrationCrack]"
                },
                {
                  "desc": "[OnSucceedAttackTail] Provoca [VibrationExplosion]"
                },
                {
                  "desc": "[OnSucceedAttack] Provoca [VibrationExplosion]<style=\"highlight\"></style>"
                }
              ]
            }
          ]
        },
        {
          "level": 4,
          "name": "Ataduras",
          "abName": "El Rey en Ataduras",
          "desc": "[CantIdentify]\nObjetivo seleccionado aleatoriamente\n[BeforeAttack] Gana (Reson. más alta de Orgullo o Pereza - 2) Alcance de Atq (máx 2)\nUmbral de Aturdimiento incrementado por [VibrationExplosion] aumenta en un 50%",
          "coinlist": [
            {
              "coindescs": [
                {
                  "desc": "[OnSucceedAttack] Inflige 6 de [Vibration]"
                },
                {
                  "desc": "[OnSucceedAttack] Inflige +3 Contador de [Vibration]"
                },
                {
                  "desc": "[OnSucceedAttack] Provoca [Switch_Vibration] en [VibrationCrack]"
                },
                {
                  "desc": "[OnSucceedAttackTail] Provoca [VibrationExplosion]"
                },
                {
                  "desc": "[OnSucceedAttackTail] Provoca [VibrationExplosion]<style=\"highlight\"></style>"
                },
                {
                  "desc": "[OnSucceedAttack] Provoca [VibrationExplosion]<style=\"highlight\"></style>"
                }
              ]
            }
          ]
        }
      ]
    },
    {
      "id": 2110711,
      "levelList": [
        {
          "level": 1,
          "name": "Triturador Dimensional",
          "abName": "Pasajero Incontrolable",
          "desc": "[BeforeAttack] Con 4+ Reson. más alta, gana +1 Alcance de Atq\n[BeforeAttack] Con menos de 10 Contador de [Charge], gasta 15% de HP para ganar +10 Contador de [Charge] (este daño no baja los HP de esta unidad a 0; redondeado hacia abajo)\n[BeforeAttack] Gasta hasta 40 Contador de [Charge] e inflige +1% de daño por cada Contador de [Charge] gastado (máx 10%)",
          "coinlist": [
            {
              "coindescs": [
                {
                  "desc": "[OnSucceedAttack] Inflige ([Charge] - 1) [DimensionRift] (máx 1)"
                },
                {
                  "desc": "[OnSucceedAttack] Gana 1 [Agility] y 1 [ChargeLoad] el siguiente turno por cada [Charge] (máx uno de cada uno por Habilidad)"
                },
                {
                  "desc": "[EnemyKill] Gana +2 Contador de [Charge]"
                }
              ]
            }
          ]
        },
        {
          "level": 3,
          "name": "Triturador Dimensional",
          "abName": "Pasajero Incontrolable",
          "desc": "[BeforeAttack] Con <style=\"highlight\">3</style>+ Reson. más alta, gana +1 Alcance de Atq\n[BeforeAttack] Con menos de 10 Contador de [Charge], gasta 15% de HP para ganar +10 Contador de [Charge] (este daño no baja los HP de esta unidad a 0; redondeado hacia abajo)\n[BeforeAttack] Gasta hasta 40 Contador de [Charge] e inflige +1% de daño por cada Contador de [Charge] gastado (máx <style=\"highlight\">20</style>%)",
          "coinlist": [
            {
              "coindescs": [
                {
                  "desc": "[OnSucceedAttack] Inflige ([Charge] - 1) [DimensionRift] (máx <style=\"highlight\">2</style>)"
                },
                {
                  "desc": "[OnSucceedAttack] Gana 1 [Agility] y 1 [ChargeLoad] el siguiente turno por cada [Charge] (máx <style=\"highlight\">2</style> de cada uno por cada Habilidad)"
                },
                {
                  "desc": "[EnemyKill] Gana +2 Contador de [Charge]<style=\"highlight\"></style>"
                }
              ]
            }
          ]
        },
        {
          "level": 4,
          "name": "Triturador Dimensional",
          "abName": "Pasajero Incontrolable",
          "desc": "[BeforeAttack] Gana +<style=\"highlight\">(Reson. más alta - 2)</style> Alcance de Atq <style=\"highlight\">(máx 2)</style>\n[BeforeAttack] Con menos de 10 Contador de [Charge], gasta <style=\"highlight\">10</style>% de HP para ganar +10 Contador de [Charge] (este daño no baja los HP de esta unidad a 0; redondeado hacia abajo)\n[BeforeAttack] Gasta hasta 40 Contador de [Charge] e inflige +1% de daño por cada Contador de [Charge] gastado (máx <style=\"highlight\">30</style>%)",
          "coinlist": [
            {
              "coindescs": [
                {
                  "desc": "[OnSucceedAttack] Inflige ([Charge] - 1) [DimensionRift] (máx 2)<style=\"highlight\"></style>"
                },
                {
                  "desc": "[OnSucceedAttack] Gana 1 [Agility] y 1 [ChargeLoad] el siguiente turno por cada [Charge] (máx <style=\"highlight\">3</style> de cada uno por cada Habilidad)"
                },
                {
                  "desc": "[EnemyKill] Gana +2 Contador de [Charge]<style=\"highlight\"></style>"
                }
              ]
            }
          ]
        }
      ]
    },
    {
      "id": 2110721,
      "levelList": [
        {
          "level": 1,
          "name": "Triturador Dimensional",
          "abName": "Pasajero Incontrolable",
          "desc": "[CantIdentify]\nObjetivo seleccionado aleatoriamente\n[BeforeAttack] Con 4+ Reson. más alta, gana +1 Alcance de Atq\n[BeforeAttack] Con Contador de [Charge] menor al Máx, gasta (Contador de [Charge] faltante x 1.5)% de HP para ganar Contador de [Charge] Máx (Contador de [Charge] Máx obtenible con este efecto: 30. Este daño no reduce la HP de esta unidad a 0; redondeado hacia abajo)\n[BeforeAttack] Gasta hasta 40 Contador de [Charge] e inflige +2% de daño por cada Contador de [Charge] gastado (máx 20%)",
          "coinlist": [
            {
              "coindescs": [
                {
                  "desc": "[OnSucceedAttack] Inflige ([Charge] - 1) [DimensionRift] (máx 2)"
                },
                {
                  "desc": "[OnSucceedAttack] Gana 1 [Agility] y 1 [ChargeLoad] el siguiente turno por cada [Charge] (máx 2 de cada uno por Habilidad)"
                },
                {
                  "desc": "[EnemyKill] Gana +2 Contador de [Charge]"
                }
              ]
            }
          ]
        },
        {
          "level": 3,
          "name": "Triturador Dimensional",
          "abName": "Pasajero Incontrolable",
          "desc": "[CantIdentify]\nObjetivo seleccionado aleatoriamente\n[BeforeAttack] Con 4+ Reson. más alta, gana +1 Alcance de Atq\n[BeforeAttack] Con Contador de [Charge] menor al Máx, gasta (Contador de [Charge] faltante x <style=\"highlight\">1.2</style>)% de HP para ganar Contador de [Charge] Máx (Contador de [Charge] Máx obtenible con este efecto: 30. Este daño no reduce la HP de esta unidad a 0; redondeado hacia abajo)\n[BeforeAttack] Gasta hasta 40 Contador de [Charge] e inflige +2% de daño por cada Contador de [Charge] gastado (máx <style=\"highlight\">40</style>%)",
          "coinlist": [
            {
              "coindescs": [
                {
                  "desc": "[OnSucceedAttack] Inflige ([Charge] - 1) [DimensionRift] (máx 2)<style=\"highlight\"></style>"
                },
                {
                  "desc": "[OnSucceedAttack] Gana 1 [Agility] y 1 [ChargeLoad] el siguiente turno por cada [Charge] (máx 2 de cada uno por Habilidad)"
                },
                {
                  "desc": "[EnemyKill] Gana +2 Contador de [Charge]<style=\"highlight\"></style>"
                }
              ]
            }
          ]
        },
        {
          "level": 4,
          "name": "Triturador Dimensional",
          "abName": "Pasajero Incontrolable",
          "desc": "[CantIdentify]\nObjetivo seleccionado aleatoriamente\n[BeforeAttack] Gana <style=\"highlight\">(Reson. más alta - 2)</style> Alcance de Atq <style=\"highlight\">(máx 2)</style>\n[BeforeAttack] Con Contador de [Charge] menor al Máx, gasta <style=\"highlight\">(missing Contador de [Charge])%</style> de HP para ganar Contador de [Charge] Máx (Contador de [Charge] Máx obtenible con este efecto: 30. Este daño no reduce la HP de esta unidad a 0; redondeado hacia abajo)\n[BeforeAttack] Gasta hasta 40 Contador de [Charge] e inflige +2% de daño por cada Contador de [Charge] gastado (máx <style=\"highlight\">60</style>%)",
          "coinlist": [
            {
              "coindescs": [
                {
                  "desc": "[OnSucceedAttack] Inflige ([Charge] - 1) [DimensionRift] (máx <style=\"highlight\">4</style>)"
                },
                {
                  "desc": "[OnSucceedAttack] Gana 1 [Agility] y 1 [ChargeLoad] el siguiente turno por cada [Charge] (máx <style=\"highlight\">3</style> de cada uno por Habilidad)"
                },
                {
                  "desc": "[EnemyKill] Gana +2 Contador de [Charge]<style=\"highlight\"></style>"
                }
              ]
            }
          ]
        }
      ]
    }
  ]
}